odoo9_addon_website_crm_recaptcha-9.0.1.0.0.99.dev10-py2.7-nspkg.pth
odoo9_addon_website_crm_recaptcha-9.0.1.0.0.99.dev10.dist-info/DESCRIPTION.rst
odoo9_addon_website_crm_recaptcha-9.0.1.0.0.99.dev10.dist-info/METADATA
odoo9_addon_website_crm_recaptcha-9.0.1.0.0.99.dev10.dist-info/RECORD
odoo9_addon_website_crm_recaptcha-9.0.1.0.0.99.dev10.dist-info/WHEEL
odoo9_addon_website_crm_recaptcha-9.0.1.0.0.99.dev10.dist-info/metadata.json
odoo9_addon_website_crm_recaptcha-9.0.1.0.0.99.dev10.dist-info/namespace_packages.txt
odoo9_addon_website_crm_recaptcha-9.0.1.0.0.99.dev10.dist-info/top_level.txt
odoo_addons/website_crm_recaptcha/README.rst
odoo_addons/website_crm_recaptcha/__init__.py
odoo_addons/website_crm_recaptcha/__openerp__.py
odoo_addons/website_crm_recaptcha/data/ir_model_data.xml
odoo_addons/website_crm_recaptcha/i18n/bg.po
odoo_addons/website_crm_recaptcha/i18n/es.po
odoo_addons/website_crm_recaptcha/i18n/eu.po
odoo_addons/website_crm_recaptcha/i18n/fr.po
odoo_addons/website_crm_recaptcha/i18n/nb_NO.po
odoo_addons/website_crm_recaptcha/i18n/pt_BR.po
odoo_addons/website_crm_recaptcha/i18n/website_crm_recaptcha.pot
odoo_addons/website_crm_recaptcha/i18n/zh_CN.po
odoo_addons/website_crm_recaptcha/views/website_crm_template.xml
